{
  "fileName": "Address.scala",
  "filePath": "protocol/src/main/scala/org/alephium/protocol/model/Address.scala",
  "url": "https://github.com/alephium/alephium/blob/master/protocol/src/main/scala/org/alephium/protocol/model/Address.scala",
  "summary": "This file contains code related to the creation and manipulation of addresses in the Alephium project. An address is a unique identifier that represents a destination for a transaction. The purpose of this code is to define the Address trait and its two implementations, Asset and Contract, which represent different types of addresses. The Address trait defines a lockupScript method that returns a LockupScript object, which is used to determine the groupIndex of the address. The groupIndex is a value that determines which group of nodes in the Alephium network is responsible for processing transactions involving this address.\n\nThe Address object also provides several utility methods for creating and manipulating addresses. The fromBase58 method takes a Base58-encoded string and returns an Address object if the string is a valid lockupScript. The asset method is a convenience method that returns an Asset address if the input string is a valid address of that type. The extractLockupScript method takes a Base58-encoded string and returns a LockupScript object if the string is a valid lockupScript. The p2pkh method creates an Asset address from a public key.\n\nThe SchnorrAddress case class represents a special type of Asset address that uses the Schnorr signature algorithm. It contains a BIP340SchnorrPublicKey object, which is used to generate a lockupScript and an unlockScript. The lockupScript is a P2SH script that is hashed to create a unique address. The unlockScript is used to spend funds from the address. The scriptByteCode field contains the bytecode for the unlockScript, which is generated from the lockupScript and the public key. The address field is an Asset address that represents the SchnorrAddress.\n\nOverall, this code provides the foundation for creating and manipulating addresses in the Alephium project. It defines the Address trait and its implementations, as well as several utility methods for working with addresses. The SchnorrAddress case class represents a special type of Asset address that uses the Schnorr signature algorithm. This code is an important part of the Alephium project, as it enables users to send and receive funds within the network.",
  "questions": "1. What is the purpose of the `Address` trait and its subclasses?\n- The `Address` trait and its subclasses define different types of addresses in the Alephium protocol, each with its own `lockupScript`.\n\n2. What is the purpose of the `SchnorrAddress` case class?\n- The `SchnorrAddress` case class represents a specific type of address that uses a BIP340 Schnorr public key and generates a corresponding `lockupScript` and `unlockScript`.\n\n3. What is the purpose of the `schnorrAddressLockupScript` string in the `Address` object?\n- The `schnorrAddressLockupScript` string defines the script used to generate a `lockupScript` for a Schnorr address, which includes verifying a BIP340 Schnorr signature during unlocking."
}