{
  "fileName": "Platform.scala",
  "filePath": "flow/src/main/scala/org/alephium/flow/setting/Platform.scala",
  "url": "https://github.com/alephium/alephium/flow/src/main/scala/org/alephium/flow/setting/Platform.scala",
  "summary": "The code defines a Scala object called `Platform` that provides functionality for getting the root path of the Alephium project. The `Platform` object is part of the `org.alephium.flow.setting` package.\n\nThe `Platform` object has two methods: `getRootPath()` and `getRootPath(env: Env)`. The first method returns the root path of the Alephium project based on the current environment. The second method returns the root path of the Alephium project based on the environment passed as an argument.\n\nThe `getRootPath()` method uses the `Env.currentEnv` variable to determine the current environment. It then checks if the `ALEPHIUM_HOME` environment variable is set. If it is set, it returns the path specified by the variable. If it is not set, it returns the path to the `.alephium` directory in the user's home directory. If the current environment is not `Env.Prod`, it returns the path to the `.alephium` directory with the environment name appended to it.\n\nThe `getRootPath(env: Env)` method works similarly to the `getRootPath()` method, but it uses the environment passed as an argument instead of the current environment.\n\nIf the root path returned by either method does not exist, the method creates the directory and logs a message indicating that the directory was created.\n\nThis code is useful for getting the root path of the Alephium project, which is needed for various operations such as reading and writing files. The `Platform` object can be used by other parts of the Alephium project to get the root path without having to duplicate the logic for determining the root path. For example, if a module needs to read a configuration file, it can use the `Platform` object to get the root path and then append the path to the configuration file to it.",
  "questions": "1. What is the purpose of this code?\n    \n    This code defines a Scala object called `Platform` that provides a method to get the root path of the Alephium project based on the current environment.\n\n2. What external dependencies does this code have?\n    \n    This code depends on the `com.typesafe.scalalogging.StrictLogging` library and the `org.alephium.protocol.Hash` and `org.alephium.util.Files` classes from the Alephium project.\n\n3. What is the license for this code?\n    \n    This code is licensed under the GNU Lesser General Public License version 3 or later."
}