{
  "fileName": "SimpleSerde.scala",
  "filePath": "flow/src/main/scala/org/alephium/flow/network/bootstrap/SimpleSerde.scala",
  "url": "https://github.com/alephium/alephium/flow/src/main/scala/org/alephium/flow/network/bootstrap/SimpleSerde.scala",
  "summary": "This file contains a trait called `SimpleSerde` which provides a simple serialization and deserialization interface for a given type `T`. This trait is used in the `org.alephium.flow.network.bootstrap` package to serialize and deserialize messages sent between nodes in the Alephium network.\n\nThe `SimpleSerde` trait defines four methods: `serializeBody`, `serialize`, `deserializeBody`, and `deserialize`. The `serializeBody` method takes an instance of type `T` and returns a `ByteString` representation of the serialized object. The `serialize` method calls `serializeBody` and prepends the length of the serialized object to the serialized data. The `deserializeBody` method takes a `ByteString` and returns a `SerdeResult[T]`, which is a wrapper around the deserialized object and any remaining bytes in the input. The `deserialize` method extracts the length of the serialized object from the input, extracts the serialized data, and calls `deserializeBody` to deserialize the data.\n\nThe `tryDeserialize` method is a convenience method that returns an `Option[Staging[T]]` instead of a `SerdeResult[Staging[T]]`. This method is used to attempt to deserialize a `ByteString` and return `None` if the deserialization fails.\n\nOverall, this trait provides a simple interface for serializing and deserializing messages in the Alephium network. It is used in conjunction with other classes and traits in the `org.alephium.flow.network.bootstrap` package to implement the network protocol. Here is an example of how this trait might be used:\n\n```scala\ncase class MyMessage(foo: Int, bar: String)\n\nobject MyMessage extends SimpleSerde[MyMessage] {\n  def serializeBody(input: MyMessage): ByteString = {\n    ByteString.fromArray(Bytes.from(input.foo) ++ Bytes.from(input.bar))\n  }\n\n  def deserializeBody(input: ByteString)(implicit groupConfig: GroupConfig): SerdeResult[MyMessage] = {\n    for {\n      foo <- SerdeUtils.extractInt(input)\n      bar <- SerdeUtils.extractString(input)\n    } yield MyMessage(foo, bar)\n  }\n}\n\nval message = MyMessage(42, \"hello\")\nval serialized = MyMessage.serialize(message)\nval deserialized = MyMessage.deserialize(serialized)\n```",
  "questions": "1. What is the purpose of this code and what does it do?\n   - This code defines a trait called `SimpleSerde` which provides serialization and deserialization methods for a given type `T`. It uses Akka and Alephium libraries to perform these operations.\n\n2. What is the license for this code and where can I find more information about it?\n   - This code is licensed under the GNU Lesser General Public License version 3 or later. More information about this license can be found at <http://www.gnu.org/licenses/>.\n\n3. What is the role of `SerdeUtils` in this code and how is it used?\n   - `SerdeUtils` is used to unwrap the result of `deserialize` method and return an `Option` of `Staging[T]`. This is useful when we want to handle cases where deserialization fails or returns `None`."
}