{
  "fileName": "MisbehaviorStorage.scala",
  "filePath": "flow/src/main/scala/org/alephium/flow/network/broker/MisbehaviorStorage.scala",
  "url": "https://github.com/alephium/alephium/flow/src/main/scala/org/alephium/flow/network/broker/MisbehaviorStorage.scala",
  "summary": "This code defines a trait called `MisbehaviorStorage` that is used to manage misbehavior of peers in the Alephium network. The trait contains several methods that allow for the storage and retrieval of information related to misbehavior, such as penalties and bans.\n\nThe `penaltyForgiveness` method returns a `Duration` object that represents the amount of time that must pass before a penalty is forgiven. This is used to determine when a peer's penalty should be removed.\n\nThe `get` method takes an `InetAddress` object representing a peer's IP address and returns an `Option` object that contains a `MisbehaviorStatus` object if the peer is found in the storage, or `None` if the peer is not found. The `MisbehaviorStatus` object contains information about the peer's current penalty status.\n\nThe `update` method takes an `InetAddress` object and a `Penalty` object and updates the peer's penalty status in the storage.\n\nThe `ban` method takes an `InetAddress` object and a `TimeStamp` object representing the time until which the peer should be banned, and adds the peer to the list of banned peers.\n\nThe `isBanned` method takes an `InetAddress` object and returns a boolean indicating whether the peer is currently banned.\n\nThe `remove` method takes an `InetAddress` object and removes the peer from the storage.\n\nThe `list` method returns a vector of `Peer` objects representing all the peers currently stored in the storage.\n\nThis trait is used in the larger Alephium project to manage misbehavior of peers in the network. It allows for the storage and retrieval of information related to penalties and bans, which can be used to prevent malicious behavior and maintain the integrity of the network. For example, if a peer is found to be misbehaving, it can be given a penalty that will prevent it from participating in the network for a certain amount of time. If the peer continues to misbehave, it can be banned from the network altogether. The `MisbehaviorStorage` trait provides a way to manage these penalties and bans in a centralized and consistent manner.",
  "questions": "1. What is the purpose of the `MisbehaviorStorage` trait?\n- The `MisbehaviorStorage` trait defines a set of methods for storing and managing misbehavior status of network peers.\n\n2. What is the `penaltyForgivness` method used for?\n- The `penaltyForgivness` method returns a duration representing the amount of time after which a penalty for a misbehaving peer should be forgiven.\n\n3. What is the `list` method used for?\n- The `list` method returns a vector of `Peer` objects representing all the peers currently stored in the misbehavior storage."
}