{
  "fileName": "BlockStateStorage.scala",
  "filePath": "flow/src/main/scala/org/alephium/flow/io/BlockStateStorage.scala",
  "url": "https://github.com/alephium/alephium/blob/master/flow/src/main/scala/org/alephium/flow/io/BlockStateStorage.scala",
  "summary": "This code defines a storage mechanism for `BlockState` objects in the Alephium project. The `BlockState` object represents the state of a block in the blockchain, including information such as the block's hash, height, and transaction data. \n\nThe `BlockStateStorage` trait defines a key-value storage interface for `BlockState` objects, where the key is a `BlockHash` object and the value is a `BlockState` object. The `storageKey` method is implemented to generate a unique key for each `BlockHash` object by appending a postfix to the byte representation of the hash.\n\nThe `BlockStateRockDBStorage` object is a companion object that extends the `RocksDBKeyValueCompanion` trait, which provides a factory method for creating instances of `BlockStateRockDBStorage`. This object takes a `RocksDBSource` object, a `ColumnFamily` object, and `WriteOptions` and `ReadOptions` objects as parameters. The `RocksDBSource` object represents the underlying RocksDB database, while the `ColumnFamily` object represents a column family within the database. The `WriteOptions` and `ReadOptions` objects are used to configure write and read operations on the database, respectively.\n\nThe `BlockStateRockDBStorage` class extends the `RocksDBKeyValueStorage` class, which provides a concrete implementation of the `KeyValueStorage` interface using RocksDB as the underlying storage engine. This class takes the same parameters as the `BlockStateRockDBStorage` object and passes them to the superclass constructor. It also mixes in the `BlockStateStorage` trait to provide the necessary implementation for the `KeyValueStorage` interface.\n\nOverall, this code provides a way to store and retrieve `BlockState` objects in a RocksDB database using a key-value storage mechanism. This is an important component of the Alephium project's blockchain infrastructure, as it allows for efficient storage and retrieval of block state data. An example usage of this code might be to store the state of each block in the blockchain as it is added to the chain, and then retrieve that state later when processing transactions or validating the chain.",
  "questions": "1. What is the purpose of this code?\n   \n   This code defines a storage mechanism for `BlockState` objects in the Alephium project using RocksDB.\n\n2. What is the relationship between `BlockStateRockDBStorage` and `BlockStateStorage`?\n   \n   `BlockStateRockDBStorage` is a concrete implementation of `BlockStateStorage` that uses RocksDB as the underlying storage mechanism.\n\n3. What is the significance of `Storages.blockStatePostfix` in the `storageKey` method?\n   \n   `Storages.blockStatePostfix` is a string constant that is appended to the byte representation of the `BlockHash` key to create a unique key for the `BlockState` value in the RocksDB database."
}